requests_oauthlib/__init__.py
requests_oauthlib/oauth1_auth.py
requests_oauthlib/oauth1_session.py
requests_oauthlib/oauth2_auth.py
requests_oauthlib/oauth2_session.py
requests_oauthlib/compliance_fixes/__init__.py
requests_oauthlib/compliance_fixes/douban.py
requests_oauthlib/compliance_fixes/ebay.py
requests_oauthlib/compliance_fixes/facebook.py
requests_oauthlib/compliance_fixes/fitbit.py
requests_oauthlib/compliance_fixes/instagram.py
requests_oauthlib/compliance_fixes/mailchimp.py
requests_oauthlib/compliance_fixes/plentymarkets.py
requests_oauthlib/compliance_fixes/slack.py
requests_oauthlib/compliance_fixes/weibo.py
requests_oauthlib/compliance_fixes/wix.py
requests_oauthlib_ac/__init__.py
requests_oauthlib_ac/oauth1_auth.py
requests_oauthlib_ac/oauth1_session.py
requests_oauthlib_ac/oauth2_auth.py
requests_oauthlib_ac/oauth2_session.py
requests_oauthlib_ac/compliance_fixes/__init__.py
requests_oauthlib_ac/compliance_fixes/douban.py
requests_oauthlib_ac/compliance_fixes/ebay.py
requests_oauthlib_ac/compliance_fixes/facebook.py
requests_oauthlib_ac/compliance_fixes/fitbit.py
requests_oauthlib_ac/compliance_fixes/instagram.py
requests_oauthlib_ac/compliance_fixes/mailchimp.py
requests_oauthlib_ac/compliance_fixes/plentymarkets.py
requests_oauthlib_ac/compliance_fixes/slack.py
requests_oauthlib_ac/compliance_fixes/weibo.py
requests_oauthlib_ac/compliance_fixes/wix.py
requests_oauthlib_ac-3.0.0.dist-info/LICENSE
requests_oauthlib_ac-3.0.0.dist-info/METADATA
requests_oauthlib_ac-3.0.0.dist-info/WHEEL
requests_oauthlib_ac-3.0.0.dist-info/top_level.txt
requests_oauthlib_ac-3.0.0.dist-info/RECORD
